source_mailchimp/__init__.py
source_mailchimp/components.py
source_mailchimp/config_migrations.py
source_mailchimp/manifest.yaml
source_mailchimp/run.py
source_mailchimp/source.py
source_mailchimp/spec.json
airbyte_source_mailchimp-2.0.37.dist-info/METADATA
airbyte_source_mailchimp-2.0.37.dist-info/WHEEL
airbyte_source_mailchimp-2.0.37.dist-info/entry_points.txt
airbyte_source_mailchimp-2.0.37.dist-info/RECORD
