Metadata-Version: 2.3
Name: airbyte-source-mailchimp
Version: 2.0.37
Summary: Source implementation for Mailchimp.
License: MIT
Author: Airbyte
Author-email: contact@airbyte.io
Requires-Python: >=3.9,<3.12
Classifier: License :: OSI Approved :: MIT License
Classifier: Programming Language :: Python :: 3
Classifier: Programming Language :: Python :: 3.9
Classifier: Programming Language :: Python :: 3.10
Classifier: Programming Language :: Python :: 3.11
Requires-Dist: airbyte-cdk
Requires-Dist: pytest (>=8.0.0,<9.0.0)
Project-URL: Documentation, https://docs.airbyte.com/integrations/sources/mailchimp
Project-URL: Homepage, https://airbyte.com
Project-URL: Repository, https://github.com/airbytehq/airbyte
